{"template":false,"numberOfChildren":10,"filePath":"C:\\Users\\User\\Desktop\\gerumap\\src\\main\\resources\\patternGalleryFiles\\pattern1.json","children":[{"type":"Concept","properties":{"selected":false,"height":81,"width":36,"originalX":171,"originalY":85,"position":{"x":171,"y":85},"lineStroke":3,"color":-39169,"name":"4343"}},{"type":"Concept","properties":{"selected":false,"height":81,"width":36,"originalX":99,"originalY":154,"position":{"x":99,"y":154},"lineStroke":3,"color":-39169,"name":"4343"}},{"type":"Concept","properties":{"selected":false,"height":81,"width":36,"originalX":122,"originalY":289,"position":{"x":122,"y":289},"lineStroke":3,"color":-39169,"name":"4343"}},{"type":"Concept","properties":{"selected":false,"height":81,"width":36,"originalX":288,"originalY":314,"position":{"x":288,"y":314},"lineStroke":3,"color":-39169,"name":"4343"}},{"type":"Concept","properties":{"selected":false,"height":81,"width":36,"originalX":444,"originalY":347,"position":{"x":444,"y":347},"lineStroke":3,"color":-39169,"name":"4343"}},{"type":"Concept","properties":{"selected":false,"height":81,"width":36,"originalX":509,"originalY":238,"position":{"x":509,"y":238},"lineStroke":3,"color":-39169,"name":"4343"}},{"type":"Concept","properties":{"selected":false,"height":81,"width":36,"originalX":491,"originalY":110,"position":{"x":491,"y":110},"lineStroke":3,"color":-39169,"name":"4343"}},{"type":"Concept","properties":{"selected":false,"height":81,"width":36,"originalX":358,"originalY":72,"position":{"x":358,"y":72},"lineStroke":3,"color":-39169,"name":"4343"}},{"type":"Connection","properties":{"firstConcept":{"selected":false,"height":81,"width":36,"originalX":358,"originalY":72,"position":{"x":358,"y":72},"lineStroke":3,"color":-39169,"name":"4343"},"secondConcept":{"selected":false,"height":81,"width":36,"originalX":288,"originalY":314,"position":{"x":288,"y":314},"lineStroke":3,"color":-39169,"name":"4343"},"lineStroke":0,"color":-16777216,"name":"Connection8"}},{"type":"Connection","properties":{"firstConcept":{"selected":false,"height":81,"width":36,"originalX":288,"originalY":314,"position":{"x":288,"y":314},"lineStroke":3,"color":-39169,"name":"4343"},"secondConcept":{"selected":false,"height":81,"width":36,"originalX":122,"originalY":289,"position":{"x":122,"y":289},"lineStroke":3,"color":-39169,"name":"4343"},"lineStroke":0,"color":-16777216,"name":"Connection9"}}],"name":"MindMap1"}